blackhole_io/__init__.py
blackhole_io/adapters/__init__.py
blackhole_io/adapters/abstract.py
blackhole_io/adapters/factory.py
blackhole_io/adapters/gcp_adapter.py
blackhole_io/adapters/local_adapter.py
blackhole_io/adapters/s3_adapter.py
blackhole_io/blackhole_file.py
blackhole_io/configs/__init__.py
blackhole_io/configs/abstract.py
blackhole_io/configs/gcp.py
blackhole_io/configs/local.py
blackhole_io/configs/s3.py
blackhole_io-0.1.0.dist-info/WHEEL
blackhole_io-0.1.0.dist-info/entry_points.txt
blackhole_io-0.1.0.dist-info/METADATA
blackhole_io-0.1.0.dist-info/RECORD
