Metadata-Version: 2.3
Name: blackhole-io
Version: 0.1.0
Summary: Add your description here
Author: fobiasmog
Author-email: fobiasmog <zbrejkin@yandex.ru>
Requires-Dist: pydantic>=2.11.7
Requires-Dist: starlette>=0.47.2
Requires-Python: >=3.13
Project-URL: Homepage, https://github.com/fobiasmog/blackhole
